LICENSE.txt
MANIFEST.in
README.md
hjlc3/__init__.py
hjlc3/hmc.pyc
hjlc3/suhan.py
hjlc3/__pycache__/__init__.cpython-311.pyc
hjlc3/__pycache__/suhan.cpython-311.pyc
hjlc3.egg-info/PKG-INFO
hjlc3.egg-info/SOURCES.txt
hjlc3.egg-info/dependency_links.txt
hjlc3.egg-info/top_level.txt
hjlc3-1.2.7.dist-info/LICENSE.txt
hjlc3-1.2.7.dist-info/METADATA
hjlc3-1.2.7.dist-info/WHEEL
hjlc3-1.2.7.dist-info/top_level.txt
hjlc3-1.2.7.dist-info/RECORD
